{
    "title": "5 Minute English",
    "description": "It is a resource that provides short and easy English exercises, focusing on grammar, vocabulary, listening, pronunciation, reading lessons, and quizzes. While offering basic lessons, it is geared towards intermediate learners exploring more complex language concepts. Popular lessons include English slang, idioms, and common errors. Additionally, there is a section explaining tricky grammar rules and sentence construction.",
    "url": "https://5minuteenglish.com/",
    "image": "/open-english-vn/images/resources/5-minute-english.png",
    "category": "General",
    "tags": ["pronunciation", "grammar", "vocabulary", "listening", "reading"],
    "free": true
  }